{"nodes": [{"id": "root_hermesworkspace_gamehronos_js_rules_js", "label": "rules.js", "file_type": "code", "source_file": "/root/hermesworkspace/GameHronos/js/rules.js", "source_location": "L1"}, {"id": "js_rules_applyunlocks", "label": "applyUnlocks()", "file_type": "code", "source_file": "/root/hermesworkspace/GameHronos/js/rules.js", "source_location": "L6"}, {"id": "js_rules_missingfortrueending", "label": "missingForTrueEnding()", "file_type": "code", "source_file": "/root/hermesworkspace/GameHronos/js/rules.js", "source_location": "L75"}], "edges": [{"source": "root_hermesworkspace_gamehronos_js_rules_js", "target": "js_rules_applyunlocks", "relation": "contains", "confidence": "EXTRACTED", "source_file": "/root/hermesworkspace/GameHronos/js/rules.js", "source_location": "L6", "weight": 1.0}, {"source": "root_hermesworkspace_gamehronos_js_rules_js", "target": "js_rules_missingfortrueending", "relation": "contains", "confidence": "EXTRACTED", "source_file": "/root/hermesworkspace/GameHronos/js/rules.js", "source_location": "L75", "weight": 1.0}], "raw_calls": [{"caller_nid": "js_rules_applyunlocks", "callee": "unlock", "is_member_call": false, "source_file": "/root/hermesworkspace/GameHronos/js/rules.js", "source_location": "L32"}, {"caller_nid": "js_rules_applyunlocks", "callee": "unlock", "is_member_call": false, "source_file": "/root/hermesworkspace/GameHronos/js/rules.js", "source_location": "L33"}, {"caller_nid": "js_rules_applyunlocks", "callee": "unlock", "is_member_call": false, "source_file": "/root/hermesworkspace/GameHronos/js/rules.js", "source_location": "L36"}, {"caller_nid": "js_rules_applyunlocks", "callee": "unlock", "is_member_call": false, "source_file": "/root/hermesworkspace/GameHronos/js/rules.js", "source_location": "L39"}, {"caller_nid": "js_rules_applyunlocks", "callee": "unlock", "is_member_call": false, "source_file": "/root/hermesworkspace/GameHronos/js/rules.js", "source_location": "L48"}, {"caller_nid": "js_rules_applyunlocks", "callee": "unlock", "is_member_call": false, "source_file": "/root/hermesworkspace/GameHronos/js/rules.js", "source_location": "L52"}, {"caller_nid": "js_rules_applyunlocks", "callee": "unlock", "is_member_call": false, "source_file": "/root/hermesworkspace/GameHronos/js/rules.js", "source_location": "L59"}, {"caller_nid": "js_rules_applyunlocks", "callee": "unlock", "is_member_call": false, "source_file": "/root/hermesworkspace/GameHronos/js/rules.js", "source_location": "L68"}]}